{
    "keep": {
        "days": true,
        "amount": 14
    },
    "auditLog": "log\\.6425b6ef59d56488746d0ccea1d2ee6caecd0fd0-audit.json",
    "files": [
        {
            "date": 1593006976892,
            "name": "log\\error-2020-06-24-08.log",
            "hash": "38dffe4bae7481b6e6f978c8e1e05a97"
        },
        {
            "date": 1593008644914,
            "name": "log\\error-2020-06-24-09.log",
            "hash": "9c9e9ab80afd15b7495b68e06d40aa4f"
        },
        {
            "date": 1593028738471,
            "name": "log\\error-2020-06-24-14.log",
            "hash": "0ee280f9ecfffb42b943089100790ca4"
        },
        {
            "date": 1593189528825,
            "name": "log\\error-2020-06-26-11.log",
            "hash": "b34a8a80e27f24d7abae02dc7ebac878"
        },
        {
            "date": 1593200339484,
            "name": "log\\error-2020-06-26-14.log",
            "hash": "b3c6e675c423c44f94aef58fa3d2838f"
        },
        {
            "date": 1593205123202,
            "name": "log\\error-2020-06-26-15.log",
            "hash": "4e8b83db74b83d3f2a118ba4a18b9510"
        },
        {
            "date": 1593277420718,
            "name": "log\\error-2020-06-27-12.log",
            "hash": "db105bdbf713c8a52574bff56518c391"
        },
        {
            "date": 1593284102139,
            "name": "log\\error-2020-06-27-13.log",
            "hash": "dad742db844a446822f7d77242302bc2"
        },
        {
            "date": 1593284806913,
            "name": "log\\error-2020-06-27-14.log",
            "hash": "25c2b8562b44ed9ac466459c32cf698c"
        },
        {
            "date": 1593459503749,
            "name": "log\\error-2020-06-29-14.log",
            "hash": "e97505fd44942e639f2a4ce2c6b0476f"
        },
        {
            "date": 1593461031490,
            "name": "log\\error-2020-06-29-15.log",
            "hash": "fb9c8bbdf5abeb0eba1674751f9e774d"
        },
        {
            "date": 1593476242170,
            "name": "log\\error-2020-06-29-19.log",
            "hash": "de413c401751b934aca7e2a06fd1d115"
        },
        {
            "date": 1593539339152,
            "name": "log\\error-2020-06-30-12.log",
            "hash": "890943dbc392181411697c2ff6be4188"
        },
        {
            "date": 1593541965205,
            "name": "log\\error-2020-06-30-13.log",
            "hash": "3ccb9d33edad7606f5f61a42b607cd82"
        },
        {
            "date": 1593543604262,
            "name": "log\\error-2020-06-30-14.log",
            "hash": "e762100380a433495894bd16f8a34971"
        },
        {
            "date": 1594048446718,
            "name": "log\\error-2020-07-06-10.log",
            "hash": "b85f93ac11bef7133e15ebc0deae8e6c"
        },
        {
            "date": 1594051914772,
            "name": "log\\error-2020-07-06-11.log",
            "hash": "4fbb06d724384ec39ed950f9e6f21ace"
        },
        {
            "date": 1594058270062,
            "name": "log\\error-2020-07-06-12.log",
            "hash": "ee0facdaa5ef0477a82cb6df61f53435"
        },
        {
            "date": 1594060093128,
            "name": "log\\error-2020-07-06-13.log",
            "hash": "dcbd5805d571618d65cb49a5d1a4842b"
        },
        {
            "date": 1594129953861,
            "name": "log\\error-2020-07-07-08.log",
            "hash": "8f9fcbfe86e40a9e9d669ecc9d3eb5d7"
        },
        {
            "date": 1594130612835,
            "name": "log\\error-2020-07-07-09.log",
            "hash": "1059454dba2d5063eff17d188883ab50"
        },
        {
            "date": 1594141573319,
            "name": "log\\error-2020-07-07-12.log",
            "hash": "e3d6c5146e05a4f68328cd909114ffb1"
        }
    ]
}